clid/__init__.py
clid/__main__.py
clid/_genres.py
clid/base.py
clid/database.py
clid/editmeta.py
clid/main.py
clid/pref.py
clid-0.5.2.dist-info/DESCRIPTION.rst
clid-0.5.2.dist-info/METADATA
clid-0.5.2.dist-info/RECORD
clid-0.5.2.dist-info/WHEEL
clid-0.5.2.dist-info/entry_points.txt
clid-0.5.2.dist-info/metadata.json
clid-0.5.2.dist-info/top_level.txt
